sepplotlib/__init__.py
sepplotlib/biseparation.py
sepplotlib/model_criticism.py
sepplotlib/separation.py
sepplotlib-1.0.1.dist-info/WHEEL
sepplotlib-1.0.1.dist-info/METADATA
sepplotlib-1.0.1.dist-info/RECORD
